medusa/__init__.py
medusa/hf_utils.py
medusa/inference/__init__.py
medusa/inference/cli.py
medusa/model/__init__.py
medusa/model/kv_cache.py
medusa/model/medusa_model.py
medusa/model/modeling_llama_kv.py
medusa/model/utils.py
medusa/train/__init__.py
medusa/train/train.py
medusa_llm-0.1.dist-info/LICENSE
medusa_llm-0.1.dist-info/METADATA
medusa_llm-0.1.dist-info/WHEEL
medusa_llm-0.1.dist-info/top_level.txt
medusa_llm-0.1.dist-info/RECORD
