Metadata-Version: 2.1
Name: medusa-llm
Version: 0.1
Summary: Simple Framework for Accelerating LLM Generation with Multiple Decoding Heads
Project-URL: Homepage, https://github.com/FasterDecoding/Medusa
Project-URL: Blog, https://sites.google.com/view/medusa-llm
Classifier: Programming Language :: Python :: 3
Classifier: License :: OSI Approved :: Apache Software License
Requires-Python: >=3.9
License-File: LICENSE
Requires-Dist: fschat
Requires-Dist: torch
Requires-Dist: transformers
Requires-Dist: accelerate
Requires-Dist: sentencepiece
Requires-Dist: protobuf
Provides-Extra: train
Requires-Dist: bitsandbytes ; extra == 'train'
Requires-Dist: wandb ; extra == 'train'
Requires-Dist: scipy ; extra == 'train'
